pyroanimate/__init__.py
pyroanimate/animate.py
pyroanimate-0.1.1.dist-info/licenses/LICENSE
pyroanimate-0.1.1.dist-info/METADATA
pyroanimate-0.1.1.dist-info/WHEEL
pyroanimate-0.1.1.dist-info/top_level.txt
pyroanimate-0.1.1.dist-info/RECORD
