Metadata-Version: 2.4
Name: pyroanimate
Version: 0.1.1
Summary: A simple animation library for Pyrogram bots
Author: dap3842
Author-email: dap3842 <afistal@mail.ru>
License: MIT License
Requires-Python: >=3.8
License-File: LICENSE
Requires-Dist: pyrogram>=2.0.0
Dynamic: author
Dynamic: license-file
Dynamic: requires-python
